inenv/__init__.py
inenv/cli.py
inenv/inenv.py
inenv/utils.py
inenv/venv.py
inenv/version.py
inenv-1.1.0.dist-info/DESCRIPTION.rst
inenv-1.1.0.dist-info/METADATA
inenv-1.1.0.dist-info/RECORD
inenv-1.1.0.dist-info/WHEEL
inenv-1.1.0.dist-info/entry_points.txt
inenv-1.1.0.dist-info/metadata.json
inenv-1.1.0.dist-info/top_level.txt
tests/__init__.py
tests/base.py
tests/test_parser.py
tests/test_version.py
