Metadata-Version: 2.0
Name: inenv
Version: 1.1.0
Summary: Simple multi virtualenv command runner
Home-page: https://github.com/pnegahdar/inenv
Author: Parham Negahdar
Author-email: pnegahdar@gmail.com
License: MIT
Keywords: venv virtualenv python tox test multivenv
Platform: UNKNOWN
Classifier: Development Status :: 4 - Beta
Classifier: Intended Audience :: Developers
Classifier: License :: OSI Approved :: MIT License
Classifier: Natural Language :: English
Classifier: Operating System :: Unix
Classifier: Programming Language :: Python :: 2
Classifier: Programming Language :: Python :: 2.7
Classifier: Programming Language :: Python :: 3
Classifier: Programming Language :: Python :: 3.5
Classifier: Programming Language :: Python :: 3.6
Classifier: Operating System :: OS Independent
Requires-Dist: atomicwrites (>=1.1.5)
Requires-Dist: click (>=4.0)
Requires-Dist: virtualenv (>=13.0.3)
Provides-Extra: tests
Requires-Dist: mock; extra == 'tests'
Requires-Dist: nose; extra == 'tests'
Requires-Dist: coverage; extra == 'tests'
Requires-Dist: yanc; extra == 'tests'
Requires-Dist: preggy; extra == 'tests'
Requires-Dist: tox; extra == 'tests'
Requires-Dist: ipdb; extra == 'tests'
Requires-Dist: coveralls; extra == 'tests'
Requires-Dist: sphinx; extra == 'tests'
